pykami-0.6.1.dist-info/METADATA
pykami-0.6.1.dist-info/WHEEL
pykami-0.6.1.dist-info/license_files/LICENSE
pykami/__init__.py
pykami/pykami.cpython-310-x86_64-linux-gnu.so
pykami-0.6.1.dist-info/RECORD
