Metadata-Version: 2.1
Name: pykami
Version: 0.6.1
Classifier: Programming Language :: Rust
Classifier: Programming Language :: Python :: Implementation :: CPython
Classifier: Programming Language :: Python :: Implementation :: PyPy
Classifier: Topic :: Text Processing :: Markup
Classifier: Development Status :: 4 - Beta
Requires-Dist: maturin
License-File: LICENSE
Summary: A python module that parses KAMI into HTML
Keywords: markup,kami,parser,html
Home-Page: https://github.com/lilith-in-starlight/pykami
Author: Katie Ampersand <katie-and@ampersandia.net>
Author-email: Katie Ampersand <katie-and@ampersandia.net>
License: MIT
Requires-Python: >=3.7
Project-URL: Source Code, https://github.com/lilith-in-starlight/pykami
